chunk_retriever_client/__init__.py
chunk_retriever_client/__version__.py
chunk_retriever_client/client.py
tests/__init__.py
tests/test_client_examples.py
tests/test_client_integration.py
tests/test_client_unit.py
tests/test_full_chain.py
chunk_retriever_client-0.2.0.dist-info/METADATA
chunk_retriever_client-0.2.0.dist-info/WHEEL
chunk_retriever_client-0.2.0.dist-info/top_level.txt
chunk_retriever_client-0.2.0.dist-info/RECORD
