Metadata-Version: 2.4
Name: chunk_retriever_client
Version: 0.2.0
Summary: Asynchronous client for Chunk Retriever microservice.
Home-page: 
Author: Your Name
Author-email: your@email.com
Classifier: Programming Language :: Python :: 3
Classifier: Operating System :: OS Independent
Requires-Python: >=3.8
Requires-Dist: aiohttp>=3.8.0
Dynamic: author
Dynamic: author-email
Dynamic: classifier
Dynamic: requires-dist
Dynamic: requires-python
Dynamic: summary
